{
    "status": "1",
    "count": "861",
    "info": "OK",
    "infocode": "10000",
    "suggestion": {
        "keywords": [],
        "cities": []
    },
    "pois": [
        {
            "id": "B0FFHDQ9BO",
            "tag": [],
            "name": "国际快递",
            "type": "生活服务;物流速递;物流速递",
            "typecode": "070500",
            "biz_type": [],
            "address": "曲阜道83号",
            "location": "117.214214,39.116996",
            "tel": "022-23375289",
            "postcode": [],
            "website": [],
            "email": [],
            "pcode": "120000",
            "pname": "北京市",
            "citycode": "022",
            "cityname": "天津市",
            "adcode": "120101",
            "adname": "东城区",
            "importance": [],
            "shopid": [],
            "poiweight": [],
            "gridcode": "5817514700",
            "distance": "26",
            "navi_poiid": [],
            "entr_location": [],
            "exit_location": [],
            "match": "0",
            "recommend": "0",
            "timestamp": [],
            "alias": [],
            "indoor_map": "0",
            "indoor_data": {
                "cpid": [],
                "floor": [],
                "truefloor": []
            },
            "groupbuy_num": "0",
            "business_area": [],
            "discount_num": "0",
            "biz_ext": {
                "rating": [],
                "cost": []
            },
            "event": [],
            "photos": [],
            "children": []
        },
        {
            "id": "B001611OPA",
            "tag": [],
            "name": "养和里小区",
            "type": "商务住宅;住宅区;住宅小区",
            "typecode": "120302",
            "biz_type": [],
            "address": "道与京路交口",
            "location": "117.214353,39.116558",
            "tel": [],
            "postcode": [],
            "website": [],
            "email": [],
            "pcode": "120000",
            "pname": "天津市",
            "citycode": "022",
            "cityname": "天津市",
            "adcode": "120101",
            "adname": "和平区",
            "importance": [],
            "shopid": [],
            "poiweight": [],
            "gridcode": "5817513720",
            "distance": "45",
            "navi_poiid": "J50F011026_78307",
            "entr_location": "117.213945,39.116560",
            "exit_location": [],
            "match": "0",
            "recommend": "0",
            "timestamp": [],
            "alias": [],
            "indoor_map": "0",
            "indoor_data": {
                "cpid": [],
                "floor": [],
                "truefloor": []
            },
            "groupbuy_num": "0",
            "business_area": [],
            "discount_num": "0",
            "biz_ext": {
                "rating": [],
                "cost": "38307.00"
            },
            "event": [],
            "photos": [
                {
                    "title": [],
                    "url": "http://store.is.autonavi.com/showpic/5594b17aa310b38d66d044ec"
                },
                {
                    "title": [],
                    "url": "http://store.is.autonavi.com/showpic/5594b17aa310b38d66d044ee"
                },
                {
                    "title": [],
                    "url": "http://store.is.autonavi.com/showpic/5865d6b23890eaf569d13e341a943f4c"
                }
            ],
            "children": []
        },
        {
            "id": "B0FFG9MMFE",
            "tag": "鸡丝凉面,重庆小面,豌杂排骨面,豌杂面,清汤排骨面",
            "name": "渝悦食客",
            "type": "餐饮服务;餐饮相关场所;餐饮相关",
            "typecode": "050000",
            "biz_type": "diner",
            "address": "曲阜道养和里1-305(公安医院)",
            "location": "117.213970,39.116810",
            "tel": [],
            "postcode": [],
            "website": [],
            "email": [],
            "pcode": "120000",
            "pname": "天津市",
            "citycode": "022",
            "cityname": "天津市",
            "adcode": "120101",
            "adname": "和平区",
            "importance": [],
            "shopid": [],
            "poiweight": [],
            "gridcode": "5817514700",
            "distance": "48",
            "navi_poiid": [],
            "entr_location": [],
            "exit_location": [],
            "match": "0",
            "recommend": "0",
            "timestamp": [],
            "alias": [],
            "indoor_map": "0",
            "indoor_data": {
                "cpid": [],
                "floor": [],
                "truefloor": []
            },
            "groupbuy_num": "0",
            "business_area": [],
            "discount_num": "0",
            "biz_ext": {
                "rating": "3.5",
                "cost": [],
                "meal_ordering": "0"
            },
            "event": [],
            "photos": [
                {
                    "title": [],
                    "url": "http://store.is.autonavi.com/showpic/9dd55a1fbd39ab5c83452770e11886b8"
                },
                {
                    "title": [],
                    "url": "http://store.is.autonavi.com/showpic/78e644c20c9c87ac5005efdd9a3325b0"
                }
            ],
            "children": []
        },
        {
            "id": "B0FFFA8H2I",
            "tag": [],
            "name": "致青春餐厅",
            "type": "餐饮服务;中餐厅;中餐厅",
            "typecode": "050100",
            "biz_type": "diner",
            "address": "小白楼浙江路23号(起士林旁)",
            "location": "117.215039,39.117258",
            "tel": "15722084915",
            "postcode": [],
            "website": [],
            "email": [],
            "pcode": "120000",
            "pname": "天津市",
            "citycode": "022",
            "cityname": "天津市",
            "adcode": "120101",
            "adname": "和平区",
            "importance": [],
            "shopid": [],
            "poiweight": [],
            "gridcode": "5817514700",
            "distance": "57",
            "navi_poiid": "J50F011026_100652",
            "entr_location": [],
            "exit_location": [],
            "match": "0",
            "recommend": "0",
            "timestamp": [],
            "alias": [],
            "indoor_map": "0",
            "indoor_data": {
                "cpid": [],
                "floor": [],
                "truefloor": []
            },
            "groupbuy_num": "0",
            "business_area": [],
            "discount_num": "0",
            "biz_ext": {
                "rating": [],
                "cost": [],
                "meal_ordering": "0"
            },
            "event": [],
            "photos": [
                {
                    "title": [],
                    "url": "http://store.is.autonavi.com/showpic/bf84b8528052468567baddfc725f224b"
                },
                {
                    "title": [],
                    "url": "http://store.is.autonavi.com/showpic/282c37736ddae9a1f530c2cdf544111c"
                }
            ],
            "children": []
        },
        {
            "id": "B0FFH7P4V2",
            "tag": "雪花牛排,芒果冷汤",
            "name": "起士林西餐厅",
            "type": "餐饮服务;外国餐厅;西餐厅(综合风味)",
            "typecode": "050201",
            "biz_type": "diner",
            "address": "小白楼浙江路",
            "location": "117.215169,39.117101",
            "tel": [],
            "postcode": [],
            "website": [],
            "email": [],
            "pcode": "120000",
            "pname": "天津市",
            "citycode": "022",
            "cityname": "天津市",
            "adcode": "120101",
            "adname": "和平区",
            "importance": [],
            "shopid": [],
            "poiweight": [],
            "gridcode": "5817514700",
            "distance": "59",
            "navi_poiid": [],
            "entr_location": [],
            "exit_location": [],
            "match": "0",
            "recommend": "0",
            "timestamp": [],
            "alias": [],
            "indoor_map": "0",
            "indoor_data": {
                "cpid": [],
                "floor": [],
                "truefloor": []
            },
            "groupbuy_num": "0",
            "business_area": [],
            "discount_num": "0",
            "biz_ext": {
                "rating": "3.5",
                "cost": [],
                "meal_ordering": "0"
            },
            "event": [],
            "photos": [],
            "children": []
        },
        {
            "id": "B001606AA7",
            "tag": "烤金针菇,石锅拌饭,烤鸡翅,章鱼拌饭,鱼籽卷,大酱汤,脆皮串,海鲜豆腐汤,金枪鱼沙拉,鸡翅,金针菇卷,炒年糕,泡菜乌冬面,炸鸡,烤甜豆,八带,辣牛肉汤,墨西哥沙拉,炒糕条,泡菜,大酱汤和石锅拌饭,丸子串,考薯蓉,鸡肉拌饭",
            "name": "土大力(小白楼店)",
            "type": "餐饮服务;外国餐厅;韩国料理",
            "typecode": "050203",
            "biz_type": "diner",
            "address": "浙江路17号(起士林旁)",
            "location": "117.215370,39.116952",
            "tel": "022-23133630",
            "postcode": [],
            "website": [],
            "email": [],
            "pcode": "120000",
            "pname": "天津市",
            "citycode": "022",
            "cityname": "天津市",
            "adcode": "120101",
            "adname": "和平区",
            "importance": [],
            "shopid": [],
            "poiweight": [],
            "gridcode": "5817514700",
            "distance": "74",
            "navi_poiid": "J50F011026_21612",
            "entr_location": [],
            "exit_location": [],
            "match": "0",
            "recommend": "0",
            "timestamp": [],
            "alias": [],
            "indoor_map": "0",
            "indoor_data": {
                "cpid": [],
                "floor": [],
                "truefloor": []
            },
            "groupbuy_num": "0",
            "business_area": [],
            "discount_num": "0",
            "biz_ext": {
                "rating": "4.5",
                "cost": "38.00",
                "meal_ordering": "0"
            },
            "event": [],
            "photos": [
                {
                    "title": [],
                    "url": "http://store.is.autonavi.com/showpic/cbc242f5a4928b7f1cfed0f0fe4842c2"
                },
                {
                    "title": [],
                    "url": "http://store.is.autonavi.com/showpic/45e291d1e8f23f8df7c43077eccc0024"
                },
                {
                    "title": [],
                    "url": "http://store.is.autonavi.com/showpic/be4c7b392531db208fc53df0d635c64c"
                }
            ],
            "children": []
        },
        {
            "id": "B0FFGPFVO5",
            "tag": [],
            "name": "酱享合炸酱面(浙江路店)",
            "type": "餐饮服务;中餐厅;特色/地方风味餐厅",
            "typecode": "050118",
            "biz_type": "diner",
            "address": "浙江路17号(土大力)",
            "location": "117.215390,39.116890",
            "tel": "022-23300109",
            "postcode": [],
            "website": [],
            "email": [],
            "pcode": "120000",
            "pname": "天津市",
            "citycode": "022",
            "cityname": "天津市",
            "adcode": "120101",
            "adname": "和平区",
            "importance": [],
            "shopid": [],
            "poiweight": [],
            "gridcode": "5817514700",
            "distance": "76",
            "navi_poiid": [],
            "entr_location": [],
            "exit_location": [],
            "match": "0",
            "recommend": "0",
            "timestamp": [],
            "alias": [],
            "indoor_map": "0",
            "indoor_data": {
                "cpid": [],
                "floor": [],
                "truefloor": []
            },
            "groupbuy_num": "0",
            "business_area": [],
            "discount_num": "0",
            "biz_ext": {
                "rating": "3.5",
                "cost": [],
                "meal_ordering": "0"
            },
            "event": [],
            "photos": [],
            "children": []
        },
        {
            "id": "B0FFHBOK8F",
            "tag": [],
            "name": "汉庭全季酒店餐厅(浙江路店)",
            "type": "餐饮服务;快餐厅;快餐厅",
            "typecode": "050300",
            "biz_type": "diner",
            "address": "浙江路15号一楼(与曲阜道交口)",
            "location": "117.215140,39.117443",
            "tel": "022-23304117",
            "postcode": [],
            "website": [],
            "email": [],
            "pcode": "120000",
            "pname": "天津市",
            "citycode": "022",
            "cityname": "天津市",
            "adcode": "120101",
            "adname": "和平区",
            "importance": [],
            "shopid": [],
            "poiweight": [],
            "gridcode": "5817514700",
            "distance": "77",
            "navi_poiid": [],
            "entr_location": [],
            "exit_location": [],
            "match": "0",
            "recommend": "0",
            "timestamp": [],
            "alias": [],
            "indoor_map": "0",
            "indoor_data": {
                "cpid": [],
                "floor": [],
                "truefloor": []
            },
            "groupbuy_num": "0",
            "business_area": [],
            "discount_num": "0",
            "biz_ext": {
                "rating": "3.5",
                "cost": [],
                "meal_ordering": "0"
            },
            "event": [],
            "photos": [],
            "children": []
        },
        {
            "id": "B0FFFW6COL",
            "tag": [],
            "name": "御缘堂",
            "type": "生活服务;洗浴推拿场所;洗浴推拿场所",
            "typecode": "071400",
            "biz_type": [],
            "address": "南京路72号曲园1楼",
            "location": "117.213730,39.116566",
            "tel": [],
            "postcode": [],
            "website": [],
            "email": [],
            "pcode": "120000",
            "pname": "天津市",
            "citycode": "022",
            "cityname": "天津市",
            "adcode": "120101",
            "adname": "和平区",
            "importance": [],
            "shopid": [],
            "poiweight": [],
            "gridcode": "5817513720",
            "distance": "79",
            "navi_poiid": [],
            "entr_location": [],
            "exit_location": [],
            "match": "0",
            "recommend": "0",
            "timestamp": [],
            "alias": [],
            "indoor_map": "0",
            "indoor_data": {
                "cpid": [],
                "floor": [],
                "truefloor": []
            },
            "groupbuy_num": "0",
            "business_area": [],
            "discount_num": "0",
            "biz_ext": {
                "rating": "3.5",
                "cost": []
            },
            "event": [],
            "photos": [
                {
                    "title": [],
                    "url": "http://store.is.autonavi.com/showpic/a160fc07cfeaf2bd26e08fca1eb08f3c"
                },
                {
                    "title": [],
                    "url": "http://store.is.autonavi.com/showpic/0949c4628c65d9dfc19b692cf5085aad"
                },
                {
                    "title": [],
                    "url": "http://store.is.autonavi.com/showpic/2217d5e52d96f7cd5dfe5c33ffbba6b9"
                }
            ],
            "children": []
        },
        {
            "id": "B0FFH7E6PA",
            "tag": [],
            "name": "千沐风(小白楼店)",
            "type": "生活服务;生活服务场所;生活服务场所",
            "typecode": "070000",
            "biz_type": [],
            "address": "浙江路17号(曲阜道口)",
            "location": "117.215430,39.116824",
            "tel": "022-23316856",
            "postcode": [],
            "website": [],
            "email": [],
            "pcode": "120000",
            "pname": "天津市",
            "citycode": "022",
            "cityname": "天津市",
            "adcode": "120101",
            "adname": "和平区",
            "importance": [],
            "shopid": [],
            "poiweight": [],
            "gridcode": "5817514700",
            "distance": "80",
            "navi_poiid": [],
            "entr_location": [],
            "exit_location": [],
            "match": "0",
            "recommend": "0",
            "timestamp": [],
            "alias": [],
            "indoor_map": "0",
            "indoor_data": {
                "cpid": [],
                "floor": [],
                "truefloor": []
            },
            "groupbuy_num": "0",
            "business_area": [],
            "discount_num": "0",
            "biz_ext": {
                "rating": "4.0",
                "cost": []
            },
            "event": [],
            "photos": [],
            "children": []
        }
    ]
}